MilanG_A5/__init__.py
MilanG_A5/__main__.py
MilanG_A5/modules/Administration.py
MilanG_A5/modules/HelloWorld.py
MilanG_A5/modules/KLetShuffle.py
MilanG_A5/modules/Manhattan.py
MilanG_A5/modules/MonoShuffle.py
MilanG_A5/modules/RollingDice.py
MilanG_A5/modules/WordCount.py
MilanG_A5/modules/__init__.py
MilanG_git_A5-1.0.10.dist-info/METADATA
MilanG_git_A5-1.0.10.dist-info/WHEEL
MilanG_git_A5-1.0.10.dist-info/entry_points.txt
MilanG_git_A5-1.0.10.dist-info/top_level.txt
MilanG_git_A5-1.0.10.dist-info/RECORD
