Metadata-Version: 2.1
Name: MilanG-git-A5
Version: 1.0.10
Summary: MilanG's Python package for APBC A0-A4
Home-page: UNKNOWN
Author: Milan Geyer
Author-email: milan.geyer@gmx.at
License: UNKNOWN
Keywords: python,first package,APBC2021
Platform: UNKNOWN
Classifier: Programming Language :: Python :: 3
Classifier: Operating System :: OS Independent
Requires-Dist: numpy
